{
  "snapshot_date": "2025-11-25",
  "cards": [
    {
      "id": "PKM-UMB",
      "name": "Umbreon VMAX Alt Art (Evolving Skies) PSA 10",
      "market_prices": {"eBay": 2150.00, "Beezie": 1950.00}, 
      "supply": {"on_chain": 8, "off_chain": 850}
    },
    {
      "id": "PKM-ZARD",
      "name": "Charizard Base Set (Unlimited) PSA 9",
      "market_prices": {"eBay": 1050.00, "Collector Crypt": 1180.00}, 
      "supply": {"on_chain": 12, "off_chain": 420}
    },
    {
      "id": "PKM-GIRA",
      "name": "Giratina V Alt Art (Lost Origin) PSA 10",
      "market_prices": {"eBay": 900.00, "Beezie": 895.00},
      "supply": {"on_chain": 25, "off_chain": 1100}
    },
    {
      "id": "PKM-GOGH",
      "name": "Pikachu with Grey Felt Hat (Van Gogh) PSA 10",
      "market_prices": {"eBay": 320.00, "Collector Crypt": 280.00},
      "supply": {"on_chain": 50, "off_chain": 3500}
    },
    {
      "id": "PKM-GENG",
      "name": "Gengar VMAX Alt Art (Fusion Strike) PSA 10",
      "market_prices": {"eBay": 650.00, "Beezie": 720.00},
      "supply": {"on_chain": 15, "off_chain": 900}
    },
    {
      "id": "PKM-LUG",
      "name": "Lugia V Alt Art (Silver Tempest) PSA 10",
      "market_prices": {"eBay": 480.00, "Collector Crypt": 430.00},
      "supply": {"on_chain": 6, "off_chain": 1200}
    },
    {
      "id": "PKM-SKULL",
      "name": "Pretend Team Skull Pikachu (JP Promo) PSA 10",
      "market_prices": {"eBay": 3100.00, "Collector Crypt": 7500.00},
      "supply": {"on_chain": 2, "off_chain": 14}
    },
    {
      "id": "PKM-MEW",
      "name": "Mew ex Paldean Fates (#232) PSA 10",
      "market_prices": {"eBay": 155.00, "Beezie": 150.00},
      "supply": {"on_chain": 40, "off_chain": 600}
    }
  ]
}
